dirty_waters-0.104.0.dist-info/licenses/LICENSE
tool/__init__.py
tool/compare_commits.py
tool/compare_packages.py
tool/extract_deps.py
tool/get_pr_info.py
tool/get_pr_review.py
tool/get_user_commit_info.py
tool/github_repo.py
tool/main.py
tool/report_diff.py
tool/report_static.py
tool/static_analysis.py
tool/tool_config.py
dirty_waters-0.104.0.dist-info/METADATA
dirty_waters-0.104.0.dist-info/WHEEL
dirty_waters-0.104.0.dist-info/entry_points.txt
dirty_waters-0.104.0.dist-info/top_level.txt
dirty_waters-0.104.0.dist-info/RECORD
