Metadata-Version: 2.4
Name: dirty-waters
Version: 0.104.0
Summary: Automatically detect software supply chain smells and issues
Author-email: Raphina Liu <raphina@kth.se>, Diogo Gaspar <dgaspar@kth.se>, Martin Monperrus <monperrus@kth.se>
License: MIT
Project-URL: Homepage, https://github.com/chains-project/dirty-waters
Project-URL: Bug Tracker, https://github.com/chains-project/dirty-waters/issues
Keywords: software supply chain,ssc,dependencies,npm
Classifier: Intended Audience :: Developers
Classifier: Topic :: Software Development :: Build Tools
Classifier: Programming Language :: Python :: 3
Classifier: License :: OSI Approved :: MIT License
Classifier: Operating System :: OS Independent
Requires-Python: >=3.12
License-File: LICENSE
Requires-Dist: attrs==25.3.0
Requires-Dist: cattrs==24.1.3
Requires-Dist: certifi==2025.4.26
Requires-Dist: charset-normalizer==3.4.2
Requires-Dist: exceptiongroup==1.3.0
Requires-Dist: GitPython==3.1.44
Requires-Dist: idna==3.10
Requires-Dist: markdown-it-py==3.0.0
Requires-Dist: numpy==2.3.0
Requires-Dist: pandas==2.3.0
Requires-Dist: platformdirs==4.3.8
Requires-Dist: PyGithub==2.6.1
Requires-Dist: pytest==8.4.0
Requires-Dist: python-dateutil==2.9.0.post0
Requires-Dist: pytz==2025.2
Requires-Dist: PyYAML==6.0.2
Requires-Dist: requests==2.32.4
Requires-Dist: requests-cache==1.2.1
Requires-Dist: six==1.17.0
Requires-Dist: tabulate==0.9.0
Requires-Dist: tqdm==4.67.1
Requires-Dist: typing_extensions==4.14.0
Requires-Dist: tzdata==2025.2
Requires-Dist: url-normalize==1.4.3
Requires-Dist: urllib3==2.5.0
Requires-Dist: xmltodict==0.14.2
Dynamic: license-file
